terraform_compliance/__init__.py
terraform_compliance/__main__.py
terraform_compliance/main.py
terraform_compliance/common/__init__.py
terraform_compliance/common/bdd_tags.py
terraform_compliance/common/defaults.py
terraform_compliance/common/error_handling.py
terraform_compliance/common/exceptions.py
terraform_compliance/common/helper.py
terraform_compliance/common/pip_helper.py
terraform_compliance/common/readable_dir.py
terraform_compliance/common/readable_plan.py
terraform_compliance/common/terraform_files.py
terraform_compliance/extensions/__init__.py
terraform_compliance/extensions/cache.py
terraform_compliance/extensions/ext_radish_bdd.py
terraform_compliance/extensions/override_radish_hookerrors.py
terraform_compliance/extensions/override_radish_step.py
terraform_compliance/extensions/security_groups.py
terraform_compliance/extensions/silent_formatter.py
terraform_compliance/extensions/terraform.py
terraform_compliance/steps/__init__.py
terraform_compliance/steps/steps.py
terraform_compliance/steps/terrain.py
terraform_compliance/steps/given/__init__.py
terraform_compliance/steps/given/i_have_name_section_configured.py
terraform_compliance/steps/then/__init__.py
terraform_compliance/steps/then/interpolations.py
terraform_compliance/steps/then/it_must_be_in.py
terraform_compliance/steps/then/it_must_contain_something.py
terraform_compliance/steps/then/it_must_have_reference_address_referenced.py
terraform_compliance/steps/then/it_must_not_be_in.py
terraform_compliance/steps/then/its_key_condition_be_value.py
terraform_compliance/steps/then/its_value_condition_be_null.py
terraform_compliance/steps/then/its_value_condition_contain.py
terraform_compliance/steps/then/its_value_condition_match_the_search_regex.py
terraform_compliance/steps/then/property_is_enabled.py
terraform_compliance/steps/then/security_group_related.py
terraform_compliance/steps/when/__init__.py
terraform_compliance/steps/when/it_contains_something.py
terraform_compliance-1.13.0.dist-info/LICENSE
terraform_compliance-1.13.0.dist-info/METADATA
terraform_compliance-1.13.0.dist-info/WHEEL
terraform_compliance-1.13.0.dist-info/entry_points.txt
terraform_compliance-1.13.0.dist-info/top_level.txt
terraform_compliance-1.13.0.dist-info/RECORD
