Metadata-Version: 2.1
Name: terraform-compliance
Version: 1.13.0
Summary: BDD test framework for terraform
Home-page: https://github.com/eerkunt/terraform-compliance
Author: Emre Erkunt
Author-email: emre.erkunt@gmail.com
License: MIT
Platform: any
Classifier: Development Status :: 4 - Beta
Classifier: Environment :: Console
Classifier: Intended Audience :: Developers
Classifier: License :: OSI Approved :: MIT License
Classifier: Operating System :: POSIX
Classifier: Operating System :: MacOS
Classifier: Operating System :: Unix
Classifier: Operating System :: Microsoft :: Windows
Classifier: Programming Language :: Python
Classifier: Programming Language :: Python :: 3.7
Classifier: Programming Language :: Python :: 3.8
Classifier: Programming Language :: Python :: 3.9
Classifier: Programming Language :: Python :: 3.10
Classifier: Programming Language :: Python :: 3.11
Classifier: Programming Language :: Python :: 3.12
Classifier: Topic :: Software Development :: Libraries :: Python Modules
License-File: LICENSE
Requires-Dist: radish-bdd==0.18.2
Requires-Dist: gitpython>=3.0.5
Requires-Dist: netaddr>=0.7.19
Requires-Dist: colorful>=0.5.4
Requires-Dist: filetype>=1.0.5
Requires-Dist: junit-xml>=1.8
Requires-Dist: lxml>=4.5.0
Requires-Dist: emoji>=0.5.4
Requires-Dist: mock>=3.0.5
Requires-Dist: semver>=2.10.2
Requires-Dist: IPython==7.16.1
Requires-Dist: diskcache>=5.1.0
Requires-Dist: orjson>=3.10.15
Provides-Extra: faster_parsing
Requires-Dist: orjson; extra == "faster-parsing"
